typedsl/__init__.py
typedsl/adapters.py
typedsl/ast.py
typedsl/nodes.py
typedsl/py.typed
typedsl/schema.py
typedsl/serialization.py
typedsl/types.py
typedsl-0.1.0.dist-info/WHEEL
typedsl-0.1.0.dist-info/METADATA
typedsl-0.1.0.dist-info/RECORD
