Metadata-Version: 2.3
Name: typedsl
Version: 0.1.0
Summary: A type-safe node system for building ASTs and DSLs in Python 3.12+
Keywords: ast,dsl,nodes,type-safe,serialization,schema,parser,compiler
Author: Jim Lundin
Author-email: Jim Lundin <JimLundin@users.noreply.github.com>
License: Apache-2.0
Classifier: Development Status :: 4 - Beta
Classifier: Intended Audience :: Developers
Classifier: License :: OSI Approved :: Apache Software License
Classifier: Programming Language :: Python :: 3
Classifier: Programming Language :: Python :: 3.12
Classifier: Programming Language :: Python :: 3.13
Classifier: Topic :: Software Development :: Libraries :: Python Modules
Classifier: Topic :: Software Development :: Compilers
Classifier: Topic :: Software Development :: Code Generators
Classifier: Typing :: Typed
Requires-Python: >=3.12
Project-URL: Documentation, https://github.com/JimLundin/typeDSL#readme
Project-URL: Homepage, https://github.com/JimLundin/typeDSL
Project-URL: Issues, https://github.com/JimLundin/typeDSL/issues
Project-URL: Repository, https://github.com/JimLundin/typeDSL
